[
    {
        "id": "SF2410298",
        "date": "2024-08-07",
        "time": "12:03:30 PM",
        "summary": "San Mateo Con Fire on Control-2",
        "category": "Medical aid",
        "location": "E 3RD AVE ,SMO",
        "latitude": null,
        "longitude": null,
        "units": "T21"
    },
    {
        "id": "SF2410297",
        "date": "2024-08-07",
        "time": "12:02:02 PM",
        "summary": "San Mateo Con Fire on Control-2",
        "category": "Public assist, water problem",
        "location": "49 BAYWOOD AVE ,SMO",
        "latitude": 37.5638732032613,
        "longitude": -122.328899317702,
        "units": "?E21"
    },
    {
        "id": "SF2410296",
        "date": "2024-08-07",
        "time": "11:54:28 AM",
        "summary": "San Mateo Con Fire on Control-2",
        "category": "Medical aid",
        "location": "GARFIELD ST ,SMO",
        "latitude": null,
        "longitude": null,
        "units": ">E23"
    },
    {
        "id": "MF2406464",
        "date": "2024-08-07",
        "time": "11:51:03 AM",
        "summary": "Menlo Park Fire on Control-1",
        "category": "Medical aid",
        "location": "SARATOGA AVE ,EPA",
        "latitude": null,
        "longitude": null,
        "units": ">E5"
    },
    {
        "id": "SF2410295",
        "date": "2024-08-07",
        "time": "11:46:47 AM",
        "summary": "San Mateo Con Fire on Control-2",
        "category": "Medical aid",
        "location": "W HILLSDALE BLVD ,SMO",
        "latitude": null,
        "longitude": null,
        "units": ">E25"
    },
    {
        "id": "RF2408624",
        "date": "2024-08-07",
        "time": "11:42:04 AM",
        "summary": "Redwood City Fire on Control-1",
        "category": "Medical aid",
        "location": "WINSLOW ST ,RCY",
        "latitude": null,
        "longitude": null,
        "units": ">E9"
    },
    {
        "id": "BF2402691",
        "date": "2024-08-07",
        "time": "11:40:25 AM",
        "summary": "San Bruno Fire on Control-3",
        "category": "Medical aid",
        "location": "SAN MATEO AVE ,SNB",
        "latitude": null,
        "longitude": null,
        "units": ">E51"
    },
    {
        "id": "CF2405354",
        "date": "2024-08-07",
        "time": "11:31:23 AM",
        "summary": "Central County Fire on Control-2",
        "category": "Medical aid",
        "location": "PALM AVE ,MLB",
        "latitude": null,
        "longitude": null,
        "units": ">E37"
    },
    {
        "id": "RF2408621",
        "date": "2024-08-07",
        "time": "11:20:00 AM",
        "summary": "Redwood City Fire on Control-1",
        "category": "Medical aid",
        "location": "BRANDY ROCK WAY ,RCY",
        "latitude": null,
        "longitude": null,
        "units": "E12"
    }
]