[
    {
        "id": "DF2301935",
        "date": "2023-09-14",
        "time": "5:07:07 AM",
        "summary": "County Fire on Control-1",
        "category": "Medical aid",
        "location": "YORKSHIRE LN ,EML",
        "latitude": null,
        "longitude": null,
        "units": "?E10"
    },
    {
        "id": "NF2310143",
        "date": "2023-09-14",
        "time": "4:54:52 AM",
        "summary": "North County Fire on Control-3",
        "category": "Trash fire",
        "location": "909 OCEANA BLVD ,PCF",
        "latitude": 37.6419424278318,
        "longitude": -122.490139037611,
        "units": ">E71"
    },
    {
        "id": "SF2311451",
        "date": "2023-09-14",
        "time": "4:54:06 AM",
        "summary": "San Mateo Con Fire on Control-2",
        "category": "Medical aid",
        "location": "VANESSA DR ,SMO",
        "latitude": null,
        "longitude": null,
        "units": ""
    },
    {
        "id": "DF2301925",
        "date": "2023-09-14",
        "time": "9/12/2023 8:46:54 AM",
        "summary": "County Fire on Control-1",
        "category": "Medical aid",
        "location": "MADERA DR ,SOS",
        "latitude": null,
        "longitude": null,
        "units": ""
    }
]