[
    {
        "id": "BF2301632",
        "date": "2023-04-25",
        "time": "11:26:54 AM",
        "summary": "San Bruno Fire on Control-3",
        "category": "Medical aid",
        "location": "EL CAMINO REAL ,SNB",
        "latitude": null,
        "longitude": null,
        "units": "?Q62"
    },
    {
        "id": "MF2303981",
        "date": "2023-04-25",
        "time": "11:26:12 AM",
        "summary": "Menlo Park Fire on Control-1",
        "category": "Medical aid",
        "location": "BAY RD #12 ,EPA",
        "latitude": null,
        "longitude": null,
        "units": "E2"
    },
    {
        "id": "FF2302558",
        "date": "2023-04-25",
        "time": "11:15:15 AM",
        "summary": "South San Francisco on Control-3",
        "category": "Medical aid",
        "location": "S SAN FRANCISCO DR ,SSF",
        "latitude": null,
        "longitude": null,
        "units": ">E65"
    },
    {
        "id": "BF2301631",
        "date": "2023-04-25",
        "time": "11:14:49 AM",
        "summary": "San Bruno Fire on Control-3",
        "category": "Tree down",
        "location": "2201 PRINCETON DR ,SNB",
        "latitude": 37.6198040748463,
        "longitude": -122.43047159743,
        "units": ">T51"
    },
    {
        "id": "MF2303980",
        "date": "2023-04-25",
        "time": "11:14:16 AM",
        "summary": "Menlo Park Fire on Control-1",
        "category": "Wires down (not sparking)",
        "location": "126 DUMBARTON AVE ,NFO",
        "latitude": 37.4718654934137,
        "longitude": -122.212022590157,
        "units": "E9"
    },
    {
        "id": "BF2301630",
        "date": "2023-04-25",
        "time": "10:57:35 AM",
        "summary": "San Bruno Fire on Control-3",
        "category": "Fire alarm - water flow",
        "location": "1150 EL CAMINO REAL #300 ,SNB",
        "latitude": 37.6364709775789,
        "longitude": -122.416803771445,
        "units": ">E51 CM31X1"
    },
    {
        "id": "BF2301629",
        "date": "2023-04-25",
        "time": "10:47:20 AM",
        "summary": "San Bruno Fire on Control-3",
        "category": "Public assist",
        "location": "1551 SEQUOIA AVE ,SNB",
        "latitude": 37.6279665927151,
        "longitude": -122.445738693621,
        "units": ">E52"
    }
]