[
    {
        "id": "FF2202963",
        "date": "2022-05-29",
        "time": "8:43:59 AM",
        "summary": "South San Francisco on Control-3",
        "category": "Medical aid",
        "location": "HICKEY BLVD #27 ,SSF",
        "latitude": null,
        "longitude": null,
        "units": "E94"
    },
    {
        "id": "SF2206038",
        "date": "2022-05-29",
        "time": "8:22:55 AM",
        "summary": "San Mateo Con Fire on Control-2",
        "category": "Medical aid",
        "location": "W 3RD AVE #1108 ,SMO",
        "latitude": null,
        "longitude": null,
        "units": ""
    },
    {
        "id": "DF2200909",
        "date": "2022-05-29",
        "time": "8:21:31 AM",
        "summary": "County Fire on Control-1",
        "category": "Tree down",
        "location": "GAZOS CREEK RD / CLOVERDALE RD",
        "latitude": 37.1861695651266,
        "longitude": -122.34001870939,
        "units": "E1761 E59"
    },
    {
        "id": "MF2204037",
        "date": "2022-05-29",
        "time": "8:18:08 AM",
        "summary": "Menlo Park Fire on Control-1",
        "category": "Medical aid",
        "location": "MADERA AVE ,MNP",
        "latitude": null,
        "longitude": null,
        "units": ">E77"
    },
    {
        "id": "HF2201171",
        "date": "2022-05-29",
        "time": "8:16:36 AM",
        "summary": "Coastside Fire on Control-1",
        "category": "Vehicle fire",
        "location": "12011 SAN MATEO RD ,SON",
        "latitude": 37.4802223581535,
        "longitude": -122.406975801512,
        "units": ">E40"
    }
]