[
    {
        "id": "BF2401530",
        "date": "2024-04-26",
        "time": "8:04:10 PM",
        "summary": "San Bruno Fire on Control-3",
        "category": "Medical aid",
        "location": "EL CAMINO REAL ,SNB",
        "latitude": null,
        "longitude": null,
        "units": "E51"
    },
    {
        "id": "FF2402385",
        "date": "2024-04-26",
        "time": "7:55:57 PM",
        "summary": "South San Francisco on Control-3",
        "category": "Medical aid",
        "location": "PECKS LN ,SSF",
        "latitude": null,
        "longitude": null,
        "units": ">E65"
    },
    {
        "id": "LF2400374",
        "date": "2024-04-26",
        "time": "7:54:55 PM",
        "summary": "Colma Fire on Control-3",
        "category": "Medical aid",
        "location": "WASHINGTON ST ,BRD",
        "latitude": null,
        "longitude": null,
        "units": ">E86"
    },
    {
        "id": "SF2405329",
        "date": "2024-04-26",
        "time": "7:35:12 PM",
        "summary": "San Mateo Con Fire on Control-2",
        "category": "Medical aid",
        "location": "BALDWIN AVE #617 ,SMO",
        "latitude": null,
        "longitude": null,
        "units": ""
    }
]