[
    {
        "id": "MF2304906",
        "date": "2023-05-30",
        "time": "1:42:23 PM",
        "summary": "Menlo Park Fire on Control-1",
        "category": "Medical aid",
        "location": "EL CAMINO REAL ,MNP",
        "latitude": null,
        "longitude": null,
        "units": "?E6"
    },
    {
        "id": "DF2301301",
        "date": "2023-05-30",
        "time": "1:39:14 PM",
        "summary": "County Fire on Control-1",
        "category": "Gas main break",
        "location": "SB 280 / EDGEWOOD RD OFF RAMP  ,SOS",
        "latitude": 37.4725551032949,
        "longitude": -122.296399060905,
        "units": "CM11X1 E19 E27 ?TAC15 ?BC2?E33 ?T17"
    },
    {
        "id": "MF2304905",
        "date": "2023-05-30",
        "time": "1:35:38 PM",
        "summary": "Menlo Park Fire on Control-1",
        "category": "Medical aid",
        "location": "WILLOW RD #207 ,MNP",
        "latitude": null,
        "longitude": null,
        "units": ">E1"
    },
    {
        "id": "NF2306210",
        "date": "2023-05-30",
        "time": "1:30:25 PM",
        "summary": "North County Fire on Control-3",
        "category": "Medical aid",
        "location": "CALLAN BLVD ,DCY",
        "latitude": null,
        "longitude": null,
        "units": ">E94"
    },
    {
        "id": "BF2302064",
        "date": "2023-05-30",
        "time": "1:28:31 PM",
        "summary": "San Bruno Fire on Control-3",
        "category": "Medical aid",
        "location": "CRYSTAL SPRINGS RD ,SNB",
        "latitude": null,
        "longitude": null,
        "units": ">E51"
    },
    {
        "id": "NF2306208",
        "date": "2023-05-30",
        "time": "1:21:23 PM",
        "summary": "North County Fire on Control-3",
        "category": "Medical aid",
        "location": "TERRACE VIEW CT #8 ,DCY",
        "latitude": null,
        "longitude": null,
        "units": ">T95"
    },
    {
        "id": "HF2301571",
        "date": "2023-05-30",
        "time": "1:16:50 PM",
        "summary": "Coastside Fire on Control-1",
        "category": "Medical aid",
        "location": "BLOOM LN #1223 ,HMB",
        "latitude": null,
        "longitude": null,
        "units": ""
    },
    {
        "id": "RF2306148",
        "date": "2023-05-30",
        "time": "12:49:42 PM",
        "summary": "Redwood City Fire on Control-1",
        "category": "Landscape fire",
        "location": "775 9TH AVE ,NFO",
        "latitude": 37.4781266957523,
        "longitude": -122.196624931959,
        "units": ">PR3B >E11"
    }
]