[
    {
        "id": "SF2204696",
        "date": "2022-04-27",
        "time": "10:59:55 PM",
        "summary": "San Mateo Con Fire on Control-2",
        "category": "Medical aid",
        "location": "NOTRE DAME AVE ,BLM",
        "latitude": null,
        "longitude": null,
        "units": ">E14"
    },
    {
        "id": "LF2200365",
        "date": "2022-04-27",
        "time": "10:55:09 PM",
        "summary": "Colma Fire on Control-3",
        "category": "Lock out - residential",
        "location": "101 A ST #312 ,BRD",
        "latitude": 37.6867674483913,
        "longitude": -122.467951201326,
        "units": ">E86"
    },
    {
        "id": "FF2202290",
        "date": "2022-04-27",
        "time": "10:46:49 PM",
        "summary": "South San Francisco on Control-3",
        "category": "Medical aid",
        "location": "LOMITAS AVE ,SSF",
        "latitude": null,
        "longitude": null,
        "units": ">E63"
    },
    {
        "id": "FF2202289",
        "date": "2022-04-27",
        "time": "10:25:45 PM",
        "summary": "South San Francisco on Control-3",
        "category": "Fire alarm - manual",
        "location": "210 EL CAMINO REAL ,SSF",
        "latitude": 37.6437019194625,
        "longitude": -122.424489931758,
        "units": ">E61"
    }
]