[
    {
        "id": "NF2308128",
        "date": "2023-07-23",
        "time": "10:02:56 AM",
        "summary": "North County Fire on Control-3",
        "category": "Full assignment response",
        "location": "365 TALBOT AVE ,PCF",
        "latitude": 37.633941962832,
        "longitude": -122.48793201567,
        "units": "E71 BC120 E72 TAC35 CM31X2?E95 ?T95"
    },
    {
        "id": "MF2306514",
        "date": "2023-07-23",
        "time": "9:56:11 AM",
        "summary": "Menlo Park Fire on Control-1",
        "category": "Public assist",
        "location": "2162 COOLEY AVE ,EPA",
        "latitude": 37.4648591678337,
        "longitude": -122.139007388779,
        "units": ">E2"
    },
    {
        "id": "SF2309093",
        "date": "2023-07-23",
        "time": "9:47:55 AM",
        "summary": "San Mateo Con Fire on Control-2",
        "category": "Medical aid",
        "location": "DAVEY GLEN RD #415 ,BLM",
        "latitude": null,
        "longitude": null,
        "units": ">E23"
    },
    {
        "id": "FF2304264",
        "date": "2023-07-23",
        "time": "9:47:47 AM",
        "summary": "South San Francisco on Control-3",
        "category": "Medical aid",
        "location": "DUVAL DR ,SSF",
        "latitude": null,
        "longitude": null,
        "units": ">E94"
    },
    {
        "id": "MF2306513",
        "date": "2023-07-23",
        "time": "9:45:23 AM",
        "summary": "Menlo Park Fire on Control-1",
        "category": "Medical aid",
        "location": "VALPARAISO AVE ,WMP",
        "latitude": null,
        "longitude": null,
        "units": ">E4"
    },
    {
        "id": "SF2309090",
        "date": "2023-07-23",
        "time": "8:55:59 AM",
        "summary": "San Mateo Con Fire on Control-2",
        "category": "Medical aid",
        "location": "SOUTHRIDGE CT ,SMO",
        "latitude": null,
        "longitude": null,
        "units": "E27"
    }
]