[
    {
        "id": "WF2301015",
        "date": "2023-05-28",
        "time": "2:20:49 PM",
        "summary": "Woodside Fire on Control-3",
        "category": "Medical aid",
        "location": "WESTRIDGE DR ,PVY",
        "latitude": null,
        "longitude": null,
        "units": "E8"
    },
    {
        "id": "FF2303180",
        "date": "2023-05-28",
        "time": "2:19:34 PM",
        "summary": "South San Francisco on Control-3",
        "category": "Medical aid",
        "location": "EL CAMINO REAL ,SSF",
        "latitude": null,
        "longitude": null,
        "units": ">E63"
    },
    {
        "id": "CF2303892",
        "date": "2023-05-28",
        "time": "2:15:10 PM",
        "summary": "Central County Fire on Control-2",
        "category": "Medical aid",
        "location": "SAN REY AVE ,MLB",
        "latitude": null,
        "longitude": null,
        "units": "E51"
    },
    {
        "id": "FF2303179",
        "date": "2023-05-28",
        "time": "2:11:58 PM",
        "summary": "South San Francisco on Control-3",
        "category": "Medical aid",
        "location": "HEMLOCK AVE ,SSF",
        "latitude": null,
        "longitude": null,
        "units": ">E65"
    },
    {
        "id": "RF2306094",
        "date": "2023-05-28",
        "time": "1:36:24 PM",
        "summary": "Redwood City Fire on Control-1",
        "category": "Medical aid",
        "location": "REDWOOD AVE ,RCY",
        "latitude": null,
        "longitude": null,
        "units": "E10"
    },
    {
        "id": "WF2301014",
        "date": "2023-05-28",
        "time": "1:30:13 PM",
        "summary": "Woodside Fire on Control-3",
        "category": "Full assignment response",
        "location": "211 LA QUESTA WAY ,WDS",
        "latitude": 37.4317354821019,
        "longitude": -122.25334679538,
        "units": "CM11X3 TAC15 >E7 >BC2 >SQ407>M107 >E19"
    }
]