[
    {
        "id": "NF2400953",
        "date": "2024-01-23",
        "time": "9:24:51 AM",
        "summary": "North County Fire on Control-3",
        "category": "Medical aid",
        "location": "BAY RIDGE DR ,DCY",
        "latitude": null,
        "longitude": null,
        "units": "E93"
    },
    {
        "id": "RF2400845",
        "date": "2024-01-23",
        "time": "9:14:23 AM",
        "summary": "Redwood City Fire on Control-1",
        "category": "Medical aid",
        "location": "SHASTA ST / UNDER WOODSIDE RD",
        "latitude": null,
        "longitude": null,
        "units": ">E11"
    },
    {
        "id": "RF2400843",
        "date": "2024-01-23",
        "time": "9:09:49 AM",
        "summary": "Redwood City Fire on Control-1",
        "category": "Medical aid",
        "location": "MAIN ST #207 ,RCY",
        "latitude": null,
        "longitude": null,
        "units": ">T9"
    },
    {
        "id": "RF2400842",
        "date": "2024-01-23",
        "time": "9:09:10 AM",
        "summary": "Redwood City Fire on Control-1",
        "category": "Medical aid",
        "location": "CENTER ST ,SNC",
        "latitude": null,
        "longitude": null,
        "units": ">E13"
    }
]