[
    {
        "id": "RF2302101",
        "date": "2023-02-20",
        "time": "6:30:32 PM",
        "summary": "Redwood City Fire on Control-1",
        "category": "Medical aid",
        "location": "WOODSIDE RD #4203 ,RCY",
        "latitude": null,
        "longitude": null,
        "units": "E9"
    },
    {
        "id": "SF2302282",
        "date": "2023-02-20",
        "time": "6:25:43 PM",
        "summary": "San Mateo Con Fire on Control-2",
        "category": "Medical aid",
        "location": "HACIENDA ST #A ,SMO",
        "latitude": null,
        "longitude": null,
        "units": ">E23"
    },
    {
        "id": "RF2302100",
        "date": "2023-02-20",
        "time": "6:17:03 PM",
        "summary": "Redwood City Fire on Control-1",
        "category": "Medical aid",
        "location": "GORDON ST #G6 ,RCY",
        "latitude": null,
        "longitude": null,
        "units": ">E10"
    },
    {
        "id": "HF2300622",
        "date": "2023-02-20",
        "time": "6:14:04 PM",
        "summary": "Coastside Fire on Control-1",
        "category": "Medical aid",
        "location": "ST ,MON",
        "latitude": null,
        "longitude": null,
        "units": ">E44"
    },
    {
        "id": "SF2302281",
        "date": "2023-02-20",
        "time": "6:13:14 PM",
        "summary": "San Mateo Con Fire on Control-2",
        "category": "Medical aid",
        "location": "ALAMEDA DE LAS PULGAS #214 ,BLM",
        "latitude": null,
        "longitude": null,
        "units": ">E15"
    }
]