[
    {
        "id": "RF2206669",
        "date": "2022-07-05",
        "time": "11:45:53 AM",
        "summary": "Redwood City Fire on Control-1",
        "category": "Medical aid",
        "location": "SALT CT ,RWS",
        "latitude": null,
        "longitude": null,
        "units": "E20"
    },
    {
        "id": "HF2201499",
        "date": "2022-07-05",
        "time": "11:42:39 AM",
        "summary": "Coastside Fire on Control-1",
        "category": "Medical aid",
        "location": "MIRAMONTES AVE ,HMB",
        "latitude": null,
        "longitude": null,
        "units": "E40"
    },
    {
        "id": "SF2207721",
        "date": "2022-07-05",
        "time": "11:40:29 AM",
        "summary": "San Mateo Con Fire on Control-2",
        "category": "Smoke investigation",
        "location": "19TH AVE / PACIFIC BLVD",
        "latitude": 37.5516886193177,
        "longitude": -122.308606098067,
        "units": "E23"
    },
    {
        "id": "NF2206856",
        "date": "2022-07-05",
        "time": "11:32:04 AM",
        "summary": "North County Fire on Control-3",
        "category": "Medical aid",
        "location": "BRIGHTON RD ,PCF",
        "latitude": null,
        "longitude": null,
        "units": ">E71"
    },
    {
        "id": "SF2207720",
        "date": "2022-07-05",
        "time": "11:31:04 AM",
        "summary": "San Mateo Con Fire on Control-2",
        "category": "Medical aid",
        "location": "PARROTT DR ,SMO",
        "latitude": null,
        "longitude": null,
        "units": ">E25"
    },
    {
        "id": "RF2206668",
        "date": "2022-07-05",
        "time": "11:25:02 AM",
        "summary": "Redwood City Fire on Control-1",
        "category": "Medical aid",
        "location": "LA MESA DR ,SNC",
        "latitude": null,
        "longitude": null,
        "units": ">E18"
    }
]