[
    {
        "id": "WF2401000",
        "date": "2024-06-22",
        "time": "4:16:35 PM",
        "summary": "Woodside Fire on Control-3",
        "category": "Medical aid",
        "location": "PORTOLA RD #29B ,PVY",
        "latitude": null,
        "longitude": null,
        "units": ">E8"
    },
    {
        "id": "FF2403557",
        "date": "2024-06-22",
        "time": "4:15:00 PM",
        "summary": "South San Francisco on Control-3",
        "category": "Medical aid",
        "location": "MILLER AVE #1 ,SSF",
        "latitude": null,
        "longitude": null,
        "units": ">E61"
    },
    {
        "id": "SF2408030",
        "date": "2024-06-22",
        "time": "4:05:44 PM",
        "summary": "San Mateo Con Fire on Control-2",
        "category": "Medical aid",
        "location": "AVE ,SMO",
        "latitude": null,
        "longitude": null,
        "units": ">E23"
    },
    {
        "id": "DF2401123",
        "date": "2024-06-22",
        "time": "3:53:20 PM",
        "summary": "County Fire on Control-1",
        "category": "Medical aid",
        "location": "SAWYER CAMP TRL ,SON",
        "latitude": null,
        "longitude": null,
        "units": ">TAC15 >BC11 >U17 >E17"
    }
]