[
    {
        "id": "WF2401073",
        "date": "2024-07-04",
        "time": "12:36:21 AM",
        "summary": "Woodside Fire on Control-3",
        "category": "Medical aid",
        "location": "WOODSIDE RD / SOUTHGATE DR",
        "latitude": null,
        "longitude": null,
        "units": ">E7"
    },
    {
        "id": "SF2408605",
        "date": "2024-07-04",
        "time": "7/3/2024 11:13:10 PM",
        "summary": "San Mateo Con Fire on Control-2",
        "category": "Water rescue response",
        "location": "BEACH PARK BLVD / EGRET ST",
        "latitude": 37.5701830333431,
        "longitude": -122.257213308969,
        "units": ">BOAT11 >AB77 >JS28 >BC5 >E28CM51X1 >CG22A"
    }
]