[
    {
        "id": "DF2300904",
        "date": "2023-03-23",
        "time": "1:38:56 PM",
        "summary": "County Fire on Control-1",
        "category": "Medical aid",
        "location": "E BAYSHORE RD #G9 ,SOS",
        "latitude": null,
        "longitude": null,
        "units": "E77"
    },
    {
        "id": "RF2303702",
        "date": "2023-03-23",
        "time": "1:34:24 PM",
        "summary": "Redwood City Fire on Control-1",
        "category": "Wires down (not sparking)",
        "location": "JEFFERSON AVE / AVENUE DEL ORA",
        "latitude": 37.4736067476158,
        "longitude": -122.240069277415,
        "units": ">E19"
    },
    {
        "id": "MF2303066",
        "date": "2023-03-23",
        "time": "1:19:18 PM",
        "summary": "Menlo Park Fire on Control-1",
        "category": "Fire alarm - smoke detector",
        "location": "2575 SAND HILL RD ,MNP",
        "latitude": 37.4197700506166,
        "longitude": -122.20392567363,
        "units": ">E4"
    },
    {
        "id": "RF2303701",
        "date": "2023-03-23",
        "time": "12:52:50 PM",
        "summary": "Redwood City Fire on Control-1",
        "category": "Grass fire",
        "location": "3728 COUNTRY CLUB DR ,RCY",
        "latitude": 37.4575211961357,
        "longitude": -122.250386450033,
        "units": ">E12"
    },
    {
        "id": "FF2301874",
        "date": "2023-03-23",
        "time": "12:23:19 PM",
        "summary": "South San Francisco on Control-3",
        "category": "Sparking/arcing wires down",
        "location": "TENNIS DR / ORANGE AVE",
        "latitude": 37.6550155758715,
        "longitude": -122.42422287622,
        "units": ">E63"
    }
]