[
    {
        "id": "RF2207581",
        "date": "2022-07-30",
        "time": "11:04:30 AM",
        "summary": "Redwood City Fire on Control-1",
        "category": "Medical aid",
        "location": "EL CAMINO REAL #505 ,RCY",
        "latitude": null,
        "longitude": null,
        "units": "E3"
    },
    {
        "id": "NF2207829",
        "date": "2022-07-30",
        "time": "10:56:48 AM",
        "summary": "North County Fire on Control-3",
        "category": "Medical aid",
        "location": "JOHN DALY BLVD ,DCY",
        "latitude": null,
        "longitude": null,
        "units": ">E92"
    },
    {
        "id": "FF2204187",
        "date": "2022-07-30",
        "time": "10:48:21 AM",
        "summary": "South San Francisco on Control-3",
        "category": "Medical aid",
        "location": "FRANCISCO DR ,SSF",
        "latitude": null,
        "longitude": null,
        "units": ">E61"
    },
    {
        "id": "SF2208778",
        "date": "2022-07-30",
        "time": "10:48:00 AM",
        "summary": "San Mateo Con Fire on Control-2",
        "category": "Medical aid",
        "location": "S QUEBEC ST ,SMO",
        "latitude": null,
        "longitude": null,
        "units": ">E24"
    }
]