[
    {
        "id": "FF2305294",
        "date": "2023-09-15",
        "time": "1:32:07 AM",
        "summary": "South San Francisco on Control-3",
        "category": "Medical aid",
        "location": "EL CAMPO DR ,SSF",
        "latitude": null,
        "longitude": null,
        "units": ">E63"
    },
    {
        "id": "CF2306555",
        "date": "2023-09-15",
        "time": "1:21:28 AM",
        "summary": "Central County Fire on Control-2",
        "category": "Medical aid",
        "location": "TERRIER PL ,HIL",
        "latitude": null,
        "longitude": null,
        "units": ">E33"
    },
    {
        "id": "MF2308114",
        "date": "2023-09-15",
        "time": "1:04:34 AM",
        "summary": "Menlo Park Fire on Control-1",
        "category": "Medical aid",
        "location": "HERMOSA WAY ,MNP",
        "latitude": null,
        "longitude": null,
        "units": ">E6"
    },
    {
        "id": "DF2301925",
        "date": "2023-09-15",
        "time": "9/12/2023 8:46:54 AM",
        "summary": "County Fire on Control-1",
        "category": "Medical aid",
        "location": "MADERA DR ,SOS",
        "latitude": null,
        "longitude": null,
        "units": ""
    }
]