[
    {
        "id": "HF2301208",
        "date": "2023-04-11",
        "time": "10:34:22 AM",
        "summary": "Coastside Fire on Control-1",
        "category": "Medical aid",
        "location": "KELLY AVE ,HMB",
        "latitude": null,
        "longitude": null,
        "units": ">E41"
    },
    {
        "id": "FF2302270",
        "date": "2023-04-11",
        "time": "10:27:15 AM",
        "summary": "South San Francisco on Control-3",
        "category": "Medical aid",
        "location": "HERMOSA LN #2 ,SSF",
        "latitude": null,
        "longitude": null,
        "units": ""
    },
    {
        "id": "CF2302748",
        "date": "2023-04-11",
        "time": "10:25:03 AM",
        "summary": "Central County Fire on Control-2",
        "category": "Medical aid",
        "location": "TUOLUMNE CT ,MLB",
        "latitude": null,
        "longitude": null,
        "units": ">E38"
    },
    {
        "id": "MF2303625",
        "date": "2023-04-11",
        "time": "10:22:59 AM",
        "summary": "Menlo Park Fire on Control-1",
        "category": "Odor investigation",
        "location": "4401 FAIR OAKS AVE ,NFO",
        "latitude": 37.4737298896614,
        "longitude": -122.189318193525,
        "units": ">E11"
    },
    {
        "id": "SF2304655",
        "date": "2023-04-11",
        "time": "10:09:15 AM",
        "summary": "San Mateo Con Fire on Control-2",
        "category": "Full assignment response",
        "location": "2100 CARLMONT DR ,BLM",
        "latitude": 37.5100610951435,
        "longitude": -122.29375808412,
        "units": "CM11X4 >BC5 ?TAC15 >E14 >E15>T17"
    }
]