[
    {
        "id": "NF2404341",
        "date": "2024-04-12",
        "time": "6:24:29 PM",
        "summary": "North County Fire on Control-3",
        "category": "Medical aid",
        "location": "MADEIRA DR ,PCF",
        "latitude": null,
        "longitude": null,
        "units": ">E72"
    },
    {
        "id": "BF2401349",
        "date": "2024-04-12",
        "time": "6:23:59 PM",
        "summary": "San Bruno Fire on Control-3",
        "category": "Medical aid",
        "location": "EL CAMINO REAL ,SNB",
        "latitude": null,
        "longitude": null,
        "units": ""
    },
    {
        "id": "NF2404339",
        "date": "2024-04-12",
        "time": "5:42:44 PM",
        "summary": "North County Fire on Control-3",
        "category": "Medical aid",
        "location": "ESCUELA DR #108A ,DCY",
        "latitude": null,
        "longitude": null,
        "units": ">E95"
    }
]