[
    {
        "id": "CF2309134",
        "date": "2023-12-30",
        "time": "1:38:32 PM",
        "summary": "Central County Fire on Control-2",
        "category": "Wires down (not sparking)",
        "location": "330 BURLINGAME AVE ,BRM",
        "latitude": 37.5850331901055,
        "longitude": -122.338217620337,
        "units": "E34"
    },
    {
        "id": "SF2316533",
        "date": "2023-12-30",
        "time": "1:32:55 PM",
        "summary": "San Mateo Con Fire on Control-2",
        "category": "Medical aid",
        "location": "S NORFOLK ST #1 ,SMO",
        "latitude": null,
        "longitude": null,
        "units": ">E26"
    },
    {
        "id": "SF2316534",
        "date": "2023-12-30",
        "time": "1:32:35 PM",
        "summary": "San Mateo Con Fire on Control-2",
        "category": "Fire alarm",
        "location": "338 S FREMONT ST ,SMO",
        "latitude": 37.5676247601573,
        "longitude": -122.318324473554,
        "units": ">E24"
    },
    {
        "id": "MF2311320",
        "date": "2023-12-30",
        "time": "1:30:40 PM",
        "summary": "Menlo Park Fire on Control-1",
        "category": "Medical aid",
        "location": "RUNNYMEDE ST ,EPA",
        "latitude": null,
        "longitude": null,
        "units": ">E2"
    }
]