[
    {
        "id": "DF2201771",
        "date": "2022-10-12",
        "time": "2:44:51 PM",
        "summary": "County Fire on Control-1",
        "category": "Medical aid",
        "location": "RAINBOW DR ,EIC",
        "latitude": null,
        "longitude": null,
        "units": "E27"
    },
    {
        "id": "MF2207956",
        "date": "2022-10-12",
        "time": "2:40:04 PM",
        "summary": "Menlo Park Fire on Control-1",
        "category": "Traffic accident pd request c3",
        "location": "EB 84 / UNIVERSITY AVE",
        "latitude": 37.48645840738,
        "longitude": -122.142501801018,
        "units": ">BC101 >E77 >T2 R77 >CM11X3>TAC15"
    },
    {
        "id": "SF2212116",
        "date": "2022-10-12",
        "time": "2:38:00 PM",
        "summary": "San Mateo Con Fire on Control-2",
        "category": "Public assist, water problem",
        "location": "120 FRANKLIN PKWY ,SMO",
        "latitude": 37.5402907872064,
        "longitude": -122.29683850972,
        "units": "E23"
    },
    {
        "id": "CF2206469",
        "date": "2022-10-12",
        "time": "2:37:41 PM",
        "summary": "Central County Fire on Control-2",
        "category": "Lock out - vehicle",
        "location": "855 BROADWAY ,MLB",
        "latitude": 37.6034682525234,
        "longitude": -122.395990543396,
        "units": ">E38"
    },
    {
        "id": "CF2206468",
        "date": "2022-10-12",
        "time": "2:28:10 PM",
        "summary": "Central County Fire on Control-2",
        "category": "Medical aid",
        "location": "RHINETTE AVE #206 ,BRM",
        "latitude": null,
        "longitude": null,
        "units": ">E34"
    },
    {
        "id": "MF2207954",
        "date": "2022-10-12",
        "time": "2:23:10 PM",
        "summary": "Menlo Park Fire on Control-1",
        "category": "Public assist, water problem",
        "location": "1270 TRINITY DR ,MNP",
        "latitude": 37.4303108800624,
        "longitude": -122.213294405309,
        "units": ">E4"
    },
    {
        "id": "RF2210289",
        "date": "2022-10-12",
        "time": "2:22:21 PM",
        "summary": "Redwood City Fire on Control-1",
        "category": "Medical aid",
        "location": "LANYARD DR ,RWS",
        "latitude": null,
        "longitude": null,
        "units": ">E13"
    },
    {
        "id": "MF2207953",
        "date": "2022-10-12",
        "time": "2:19:44 PM",
        "summary": "Menlo Park Fire on Control-1",
        "category": "Medical aid",
        "location": "BERKSHIRE AVE #2 ,NFO",
        "latitude": null,
        "longitude": null,
        "units": ""
    },
    {
        "id": "BF2203230",
        "date": "2022-10-12",
        "time": "2:18:47 PM",
        "summary": "San Bruno Fire on Control-3",
        "category": "Medical aid",
        "location": "EMARON DR ,SNB",
        "latitude": null,
        "longitude": null,
        "units": ">E52"
    },
    {
        "id": "LF2200862",
        "date": "2022-10-12",
        "time": "1:49:26 PM",
        "summary": "Colma Fire on Control-3",
        "category": "Structure fire",
        "location": "1535 SULLIVAN AVE #8 ,BRD",
        "latitude": 37.6890880271325,
        "longitude": -122.471929080335,
        "units": ">PR19 E85 ?TAC35 >CM31X1 >E86>E285 >PR20 >T85"
    }
]