[
    {
        "id": "SF2311083",
        "date": "2023-09-06",
        "time": "3:41:37 AM",
        "summary": "San Mateo Con Fire on Control-2",
        "category": "Medical aid",
        "location": "PALM AVE ,SMO",
        "latitude": null,
        "longitude": null,
        "units": "E23"
    },
    {
        "id": "HF2302397",
        "date": "2023-09-06",
        "time": "3:29:13 AM",
        "summary": "Coastside Fire on Control-1",
        "category": "Fire alarm",
        "location": "230 CABRILLO HWY S ,HMB",
        "latitude": 37.4655814799176,
        "longitude": -122.434299580299,
        "units": "*>E40"
    },
    {
        "id": "MF2307867",
        "date": "2023-09-06",
        "time": "3:02:12 AM",
        "summary": "Menlo Park Fire on Control-1",
        "category": "Medical aid",
        "location": "UNIVERSITY AVE ,EPA",
        "latitude": null,
        "longitude": null,
        "units": "BC101 ?CM11X1 >E2"
    }
]