[
    {
        "id": "RF2402896",
        "date": "2024-03-15",
        "time": "12:18:24 AM",
        "summary": "Redwood City Fire on Control-1",
        "category": "Medical aid",
        "location": "FULTON ST #1 ,RCY",
        "latitude": null,
        "longitude": null,
        "units": ">E10"
    },
    {
        "id": "NF2403186",
        "date": "2024-03-15",
        "time": "12:11:38 AM",
        "summary": "North County Fire on Control-3",
        "category": "Medical aid",
        "location": "PENHURST AVE ,DCY",
        "latitude": null,
        "longitude": null,
        "units": ">E94"
    }
]