[
    {
        "id": "DF2400002",
        "date": "2024-01-01",
        "time": "4:27:15 AM",
        "summary": "County Fire on Control-1",
        "category": "Medical aid",
        "location": "ACACIA LN ,EML",
        "latitude": null,
        "longitude": null,
        "units": ""
    },
    {
        "id": "RF2400006",
        "date": "2024-01-01",
        "time": "4:08:41 AM",
        "summary": "Redwood City Fire on Control-1",
        "category": "Public assist, water problem",
        "location": "570 HAMPSHIRE AVE ,NFO",
        "latitude": 37.477858456914,
        "longitude": -122.206793594647,
        "units": ""
    }
]