[
    {
        "id": "RF2304272",
        "date": "2023-04-06",
        "time": "10:41:38 PM",
        "summary": "Redwood City Fire on Control-1",
        "category": "Medical aid",
        "location": "AVE ,RCY",
        "latitude": null,
        "longitude": null,
        "units": "E11"
    },
    {
        "id": "RF2304271",
        "date": "2023-04-06",
        "time": "10:35:43 PM",
        "summary": "Redwood City Fire on Control-1",
        "category": "Medical aid",
        "location": "HOPKINS AVE ,RCY",
        "latitude": null,
        "longitude": null,
        "units": ">E9"
    }
]