[
    {
        "id": "SF2304064",
        "date": "2023-03-28",
        "time": "10:13:33 AM",
        "summary": "San Mateo Con Fire on Control-2",
        "category": "Medical aid",
        "location": "FAIRFAX AVE ,SMO",
        "latitude": null,
        "longitude": null,
        "units": ">E32"
    },
    {
        "id": "MF2303213",
        "date": "2023-03-28",
        "time": "10:02:21 AM",
        "summary": "Menlo Park Fire on Control-1",
        "category": "Medical aid",
        "location": "EUCLID AVE ,ATN",
        "latitude": null,
        "longitude": null,
        "units": ">E4"
    },
    {
        "id": "RF2303890",
        "date": "2023-03-28",
        "time": "9:36:07 AM",
        "summary": "Redwood City Fire on Control-1",
        "category": "Pole fire",
        "location": "1221 FERNSIDE ST #TRO ,RCY",
        "latitude": 37.4606485994574,
        "longitude": -122.245311555456,
        "units": ">E10"
    }
]