[
    {
        "id": "CF2306382",
        "date": "2023-09-06",
        "time": "6:54:00 PM",
        "summary": "Central County Fire on Control-2",
        "category": "Medical aid",
        "location": "EL CAMINO REAL / HOWARD AVE",
        "latitude": null,
        "longitude": null,
        "units": "E34"
    },
    {
        "id": "MF2307892",
        "date": "2023-09-06",
        "time": "6:50:37 PM",
        "summary": "Menlo Park Fire on Control-1",
        "category": "Fire alarm - smoke detector",
        "location": "5 NEWELL CT ,EPA",
        "latitude": 37.4570617285856,
        "longitude": -122.13815381105,
        "units": ">E2"
    }
]