[
    {
        "id": "BF2202450",
        "date": "2022-08-07",
        "time": "8:43:57 PM",
        "summary": "San Bruno Fire on Control-3",
        "category": "Medical aid",
        "location": "PICCADILLY PL #12 ,SNB",
        "latitude": null,
        "longitude": null,
        "units": "E52"
    },
    {
        "id": "CF2204963",
        "date": "2022-08-07",
        "time": "8:38:28 PM",
        "summary": "Central County Fire on Control-2",
        "category": "Medical aid",
        "location": "HEMLOCK AVE ,MLB",
        "latitude": null,
        "longitude": null,
        "units": ">E37"
    },
    {
        "id": "MF2206036",
        "date": "2022-08-07",
        "time": "8:37:12 PM",
        "summary": "Menlo Park Fire on Control-1",
        "category": "Wires down (not sparking)",
        "location": "1395 KAVANAUGH DR ,EPA",
        "latitude": 37.4753596247361,
        "longitude": -122.146134768037,
        "units": "T2"
    },
    {
        "id": "FF2204334",
        "date": "2022-08-07",
        "time": "8:28:00 PM",
        "summary": "South San Francisco on Control-3",
        "category": "Medical aid",
        "location": "KENT WAY ,SSF",
        "latitude": null,
        "longitude": null,
        "units": ""
    },
    {
        "id": "WF2201100",
        "date": "2022-08-07",
        "time": "8:23:38 PM",
        "summary": "Woodside Fire on Control-3",
        "category": "Medical aid",
        "location": "JEFFERSON AVE ,WDS",
        "latitude": null,
        "longitude": null,
        "units": ""
    },
    {
        "id": "LF2200676",
        "date": "2022-08-07",
        "time": "8:14:47 PM",
        "summary": "Colma Fire on Control-3",
        "category": "Medical aid",
        "location": "WASHINGTON ST ,BRD",
        "latitude": null,
        "longitude": null,
        "units": "*>MED19"
    }
]