[
    {
        "id": "NF2406507",
        "date": "2024-06-09",
        "time": "11:53:26 AM",
        "summary": "North County Fire on Control-3",
        "category": "Public assist",
        "location": "70 EASTLAKE AVE ,PCF",
        "latitude": 37.6285729894992,
        "longitude": -122.488658986849,
        "units": ">E71"
    },
    {
        "id": "DF2401043",
        "date": "2024-06-09",
        "time": "11:49:24 AM",
        "summary": "County Fire on Control-1",
        "category": "Medical aid",
        "location": "BUNKER HILL DR ,EIC",
        "latitude": null,
        "longitude": null,
        "units": ">E17"
    },
    {
        "id": "SF2407394",
        "date": "2024-06-09",
        "time": "11:48:53 AM",
        "summary": "San Mateo Con Fire on Control-2",
        "category": "Medical aid",
        "location": "PALOS VERDES DR #106 ,SMO",
        "latitude": null,
        "longitude": null,
        "units": ">E25"
    },
    {
        "id": "RF2406229",
        "date": "2024-06-09",
        "time": "11:46:20 AM",
        "summary": "Redwood City Fire on Control-1",
        "category": "Medical aid",
        "location": "ELM ST #243A ,SNC",
        "latitude": null,
        "longitude": null,
        "units": ">E16"
    },
    {
        "id": "MF2404511",
        "date": "2024-06-09",
        "time": "6/3/2024 10:12:24 AM",
        "summary": "Menlo Park Fire on Control-1",
        "category": "Structure fire - working",
        "location": "2700 MIDDLEFIELD RD ,NFO",
        "latitude": 37.4751734033552,
        "longitude": -122.212167459715,
        "units": ">E101"
    }
]