[
    {
        "id": "NF2312771",
        "date": "2023-11-20",
        "time": "12:21:44 PM",
        "summary": "North County Fire on Control-3",
        "category": "Fire alarm - smoke detector",
        "location": "205 ROCKAWAY BEACH AVE ,PCF",
        "latitude": 37.609428017246,
        "longitude": -122.49601354809,
        "units": "E72"
    },
    {
        "id": "CF2308151",
        "date": "2023-11-20",
        "time": "12:18:36 PM",
        "summary": "Central County Fire on Control-2",
        "category": "Medical aid",
        "location": "AIRPORT BLVD ,BRM",
        "latitude": null,
        "longitude": null,
        "units": "E32"
    },
    {
        "id": "RF2312840",
        "date": "2023-11-20",
        "time": "12:17:49 PM",
        "summary": "Redwood City Fire on Control-1",
        "category": "Medical aid",
        "location": "MADDUX DR ,RCY",
        "latitude": null,
        "longitude": null,
        "units": ">E10"
    },
    {
        "id": "SF2314642",
        "date": "2023-11-20",
        "time": "12:15:30 PM",
        "summary": "San Mateo Con Fire on Control-2",
        "category": "Medical aid",
        "location": "CAMPUS DR #129 ,SMO",
        "latitude": null,
        "longitude": null,
        "units": ">E27"
    }
]