[
    {
        "id": "HF2401908",
        "date": "2024-08-24",
        "time": "2:21:59 PM",
        "summary": "Coastside Fire on Control-1",
        "category": "Public assist",
        "location": "329 MAIN ST ,HMB",
        "latitude": 37.4652318399484,
        "longitude": -122.428669569615,
        "units": "E40"
    },
    {
        "id": "WF2401418",
        "date": "2024-08-24",
        "time": "2:20:10 PM",
        "summary": "Woodside Fire on Control-3",
        "category": "Medical aid",
        "location": "LA HONDA RD / GRANDVIEW DR ,WDS",
        "latitude": null,
        "longitude": null,
        "units": "BC2 >E58 E56 R56 ?TAC15?CM11X1"
    },
    {
        "id": "NF2409348",
        "date": "2024-08-24",
        "time": "2:18:02 PM",
        "summary": "North County Fire on Control-3",
        "category": "Medical aid",
        "location": "WILSHIRE AVE ,DCY",
        "latitude": null,
        "longitude": null,
        "units": ">E91"
    },
    {
        "id": "SF2411094",
        "date": "2024-08-24",
        "time": "2:17:59 PM",
        "summary": "San Mateo Con Fire on Control-2",
        "category": "Medical aid",
        "location": "N SAN MATEO DR #105 ,SMO",
        "latitude": null,
        "longitude": null,
        "units": ">E21"
    }
]