[
    {
        "id": "WF2200547",
        "date": "2022-05-04",
        "time": "6:56:25 PM",
        "summary": "Woodside Fire on Control-3",
        "category": "Odor investigation",
        "location": "559 ROCKY WAY ,WDS",
        "latitude": 37.4599788795156,
        "longitude": -122.278583773919,
        "units": "E19"
    },
    {
        "id": "CF2202717",
        "date": "2022-05-04",
        "time": "6:51:23 PM",
        "summary": "Central County Fire on Control-2",
        "category": "Medical aid",
        "location": "RIVERA DR ,BRM",
        "latitude": null,
        "longitude": null,
        "units": ">E33"
    }
]