[
    {
        "id": "SF2205316",
        "date": "2022-05-12",
        "time": "9:38:59 PM",
        "summary": "San Mateo Con Fire on Control-2",
        "category": "Medical aid",
        "location": "WINDING WAY ,BLM",
        "latitude": null,
        "longitude": null,
        "units": ">E14"
    },
    {
        "id": "NF2204757",
        "date": "2022-05-12",
        "time": "9:21:17 PM",
        "summary": "North County Fire on Control-3",
        "category": "Medical aid",
        "location": "LONGVIEW DR ,DCY",
        "latitude": null,
        "longitude": null,
        "units": ">E94"
    },
    {
        "id": "DF2200809",
        "date": "2022-05-12",
        "time": "8:19:31 PM",
        "summary": "County Fire on Control-1",
        "category": "Traffic accident",
        "location": "16350 SKYLINE BLVD ,SKY",
        "latitude": 37.39110436221,
        "longitude": -122.28546393967,
        "units": ">E1781 ?TAC15 >R56"
    }
]