[
    {
        "id": "NF2311543",
        "date": "2023-10-19",
        "time": "2:42:05 PM",
        "summary": "North County Fire on Control-3",
        "category": "Medical aid",
        "location": "ARGUELLO BLVD ,PCF",
        "latitude": null,
        "longitude": null,
        "units": "?TAC36 ?CM31X4 ?BC17 E72"
    },
    {
        "id": "NF2311542",
        "date": "2023-10-19",
        "time": "2:39:24 PM",
        "summary": "North County Fire on Control-3",
        "category": "Medical aid",
        "location": "PARK PL ,BRS",
        "latitude": null,
        "longitude": null,
        "units": "Q62"
    },
    {
        "id": "RF2311566",
        "date": "2023-10-19",
        "time": "2:37:47 PM",
        "summary": "Redwood City Fire on Control-1",
        "category": "Medical aid",
        "location": "EL CAMINO REAL ,RCY",
        "latitude": null,
        "longitude": null,
        "units": ">E3"
    },
    {
        "id": "RF2311565",
        "date": "2023-10-19",
        "time": "2:30:29 PM",
        "summary": "Redwood City Fire on Control-1",
        "category": "Medical aid",
        "location": "REDWOOD AVE ,RCY",
        "latitude": null,
        "longitude": null,
        "units": ">E10"
    },
    {
        "id": "SF2313210",
        "date": "2023-10-19",
        "time": "2:21:38 PM",
        "summary": "San Mateo Con Fire on Control-2",
        "category": "Medical aid",
        "location": "FLORES ST #115 ,SMO",
        "latitude": null,
        "longitude": null,
        "units": ">E23"
    },
    {
        "id": "SF2313209",
        "date": "2023-10-19",
        "time": "2:20:09 PM",
        "summary": "San Mateo Con Fire on Control-2",
        "category": "Medical aid",
        "location": "S NORFOLK ST #343 ,SMO",
        "latitude": null,
        "longitude": null,
        "units": ">E26"
    },
    {
        "id": "NF2311541",
        "date": "2023-10-19",
        "time": "2:19:51 PM",
        "summary": "North County Fire on Control-3",
        "category": "Medical aid",
        "location": "HICKEY BLVD #2ND FLR ,DCY",
        "latitude": null,
        "longitude": null,
        "units": ">E94"
    },
    {
        "id": "SF2313208",
        "date": "2023-10-19",
        "time": "2:07:40 PM",
        "summary": "San Mateo Con Fire on Control-2",
        "category": "Medical aid",
        "location": "BLOCK EL CAMINO REAL ,BLM",
        "latitude": null,
        "longitude": null,
        "units": ""
    },
    {
        "id": "NF2311535",
        "date": "2023-10-19",
        "time": "1:33:10 PM",
        "summary": "North County Fire on Control-3",
        "category": "Full assignment response",
        "location": "3500 MARINA BLVD ,BRS",
        "latitude": 37.6751936812842,
        "longitude": -122.386099658654,
        "units": ">BC20 ?TAC35 CM31X5 >PR20D >E81>E181"
    },
    {
        "id": "DF2302175",
        "date": "2023-10-19",
        "time": "1:01:08 PM",
        "summary": "County Fire on Control-1",
        "category": "Medical aid",
        "location": "PESCADERO CREEK RD ,PES",
        "latitude": null,
        "longitude": null,
        "units": "*>E17"
    }
]